{
  "generated_utc": "2026-04-05T23:16:45Z",
  "dataset": "goes19SSThourly",
  "source": "https://cwcgom.aoml.noaa.gov/erddap/griddap/goes19SSThourly",
  "sensor": "GOES-19 ABI (NOAA/AOML hourly SST)",
  "retention_days": 3,
  "region": {
    "lat_min": 33.7,
    "lat_max": 39.0,
    "lon_min": -78.89,
    "lon_max": -72.21,
    "stride": 1
  },
  "units": {
    "sst": "fahrenheit"
  },
  "image_settings": {
    "colorbar": "KT_thermal",
    "sst_min_c": 4,
    "sst_max_c": 32,
    "width_px": 1800,
    "height_px": 1200
  },
  "file_count": 3,
  "best_coverage": "GOES19_SST_20260402.json",
  "files": [
    {
      "filename": "GOES19_SST_20260402.json",
      "date": "2026-04-02",
      "hour_utc": 23,
      "size_bytes": 3448005,
      "sha256": "36c98971e45623486e1c7e3488fd822531bed002722d49677fdafcebaa054185",
      "row_count": 89109,
      "ocean_count": 34425,
      "cloud_count": 54684,
      "coverage_pct": 38.6,
      "image": {
        "filename": "GOES19_SST_20260402.jpg",
        "size_bytes": 68861
      },
      "coverage_rank": 1
    },
    {
      "filename": "GOES19_SST_20260403.json",
      "date": "2026-04-03",
      "hour_utc": 23,
      "size_bytes": 3431874,
      "sha256": "81e4fb1d7c0835377321bb10b1387308eb1caba4cb86d7772fd7633b3f78c91b",
      "row_count": 89109,
      "ocean_count": 25332,
      "cloud_count": 63777,
      "coverage_pct": 28.4,
      "image": {
        "filename": "GOES19_SST_20260403.jpg",
        "size_bytes": 60063
      },
      "coverage_rank": 3
    },
    {
      "filename": "GOES19_SST_20260404.json",
      "date": "2026-04-04",
      "hour_utc": 23,
      "size_bytes": 3437125,
      "sha256": "c1705d54ebb8aa6087539600c05acfd8917c9474c1c95213f8b6bb64fd67c4c5",
      "row_count": 89109,
      "ocean_count": 28308,
      "cloud_count": 60801,
      "coverage_pct": 31.8,
      "image": {
        "filename": "GOES19_SST_20260404.jpg",
        "size_bytes": 64318
      },
      "coverage_rank": 2
    }
  ]
}